setup.py
abhi_general.egg-info/PKG-INFO
abhi_general.egg-info/SOURCES.txt
abhi_general.egg-info/dependency_links.txt
abhi_general.egg-info/requires.txt
abhi_general.egg-info/top_level.txt
abhikashyap/__init__.py
abhikashyap/abhi_general.py