Metadata-Version: 2.1
Name: abhi-general
Version: 0.0.1
Summary: Trial custom package
Author: abhikashyap10
Author-email: <abhikashyap10@gmail.com>
Keywords: python
Classifier: Development Status :: 1 - Planning
Classifier: Intended Audience :: Developers
Classifier: Programming Language :: Python :: 3
Classifier: Operating System :: Unix
Classifier: Operating System :: MacOS :: MacOS X
Classifier: Operating System :: Microsoft :: Windows
